Metadata-Version: 2.4
Name: mcp-time-server-fwj
Version: 0.1.0
Summary: An MCP Server that provides a tool to get the current time with optional timezone support
License: MIT
License-File: LICENSE
Author: User
Author-email: user@example.com
Requires-Python: >=3.10,<4.0
Classifier: License :: OSI Approved :: MIT License
Classifier: Operating System :: OS Independent
Classifier: Programming Language :: Python :: 3
Classifier: Programming Language :: Python :: 3.10
Classifier: Programming Language :: Python :: 3.11
Classifier: Programming Language :: Python :: 3.12
Classifier: Programming Language :: Python :: 3.13
Classifier: Programming Language :: Python :: 3.14
Requires-Dist: mcp (>=1.2.0,<2.0.0)
Requires-Dist: pytz (>=2024.1,<2025.0)
